MANIFEST.in
README.rst
requirements.txt
setup.py
coorblimey/__init__.py
coorblimey/geocentrics.py
coorblimey/script.py
coorblimey.egg-info/PKG-INFO
coorblimey.egg-info/SOURCES.txt
coorblimey.egg-info/dependency_links.txt
coorblimey.egg-info/entry_points.txt
coorblimey.egg-info/not-zip-safe
coorblimey.egg-info/top_level.txt