Metadata-Version: 1.0
Name: coorblimey
Version: 0.1
Summary: coorblimey is an open source Python3 library to transform geocentric coordinates to geographic, and vice versa.
Home-page: https://github.com/lo-ise/coorblimey
Author: Louise Ireland
Author-email: louireland@gmail.com
License: MIT
Platform: UNKNOWN
